codesee_util/__init__.py
codesee_util/cli.py
codesee_util/package_info.py
codesee_util-0.88.0.dist-info/LICENSE
codesee_util-0.88.0.dist-info/METADATA
codesee_util-0.88.0.dist-info/WHEEL
codesee_util-0.88.0.dist-info/entry_points.txt
codesee_util-0.88.0.dist-info/top_level.txt
codesee_util-0.88.0.dist-info/RECORD
