Metadata-Version: 2.1
Name: codesee-util
Version: 0.88.0
Summary: CodeSee Python utilities
Home-page: https://www.codesee.io
Author: CodeSee
Author-email: cubes@codesee.io
Keywords: CodeSee,continuous,understanding
Classifier: Programming Language :: Python :: 3
Classifier: License :: Other/Proprietary License
Classifier: Operating System :: OS Independent
Requires-Python: >=3.6
License-File: LICENSE
Requires-Dist: setuptools
Requires-Dist: six
Provides-Extra: pydeps
Requires-Dist: pydeps (<=1.12.4) ; extra == 'pydeps'
